{
  "vrf": {
    "id": 1,
    "client_name": "hardware",
    "vlan": [
      {
        "vlan": 321,
        "lan_ip": "1.1.1.1/24"
      }
    ],
    "crypto_ph1": "aes-cbc-128.sha1.fourteen",
    "crypto_ph2": "esp-aes.esp-sha-hmac.group14",
    "physical_interface": "eth0",
    "active": true,
    "local_as": 65002,
    "endpoint": [
      {
        "remote_ip_sec": "10.200.1.1",
        "local_ip": "192.168.1.2",
        "peer_ip": "192.168.1.1",
        "remote_as": 65001,
        "nat": false,
        "bgp": false,
        "source_interface": "Vlan200",
        "authentication": {
          "type": "psk",
          "psk": "asdasdasd",
          "local_cert": "",
          "remote_cert": "",
          "private_key": ""
        }
      }
    ]
  }
}
